{"nodes": [{"id": "scripts_rewrite_cdn_mjs", "label": "rewrite-cdn.mjs", "file_type": "code", "source_file": "scripts/rewrite-cdn.mjs", "source_location": "L1"}, {"id": "rewrite_cdn_rewritehtml", "label": "rewriteHtml()", "file_type": "code", "source_file": "scripts/rewrite-cdn.mjs", "source_location": "L55"}, {"id": "rewrite_cdn_main", "label": "main()", "file_type": "code", "source_file": "scripts/rewrite-cdn.mjs", "source_location": "L85"}], "edges": [{"source": "scripts_rewrite_cdn_mjs", "target": "promises", "relation": "imports_from", "confidence": "EXTRACTED", "source_file": "scripts/rewrite-cdn.mjs", "source_location": "L29", "weight": 1.0}, {"source": "scripts_rewrite_cdn_mjs", "target": "node_path", "relation": "imports_from", "confidence": "EXTRACTED", "source_file": "scripts/rewrite-cdn.mjs", "source_location": "L30", "weight": 1.0}, {"source": "scripts_rewrite_cdn_mjs", "target": "node_url", "relation": "imports_from", "confidence": "EXTRACTED", "source_file": "scripts/rewrite-cdn.mjs", "source_location": "L31", "weight": 1.0}, {"source": "scripts_rewrite_cdn_mjs", "target": "rewrite_cdn_rewritehtml", "relation": "contains", "confidence": "EXTRACTED", "source_file": "scripts/rewrite-cdn.mjs", "source_location": "L55", "weight": 1.0}, {"source": "scripts_rewrite_cdn_mjs", "target": "rewrite_cdn_main", "relation": "contains", "confidence": "EXTRACTED", "source_file": "scripts/rewrite-cdn.mjs", "source_location": "L85", "weight": 1.0}, {"source": "rewrite_cdn_main", "target": "rewrite_cdn_rewritehtml", "relation": "calls", "confidence": "EXTRACTED", "source_file": "scripts/rewrite-cdn.mjs", "source_location": "L106", "weight": 1.0}], "raw_calls": [{"caller_nid": "rewrite_cdn_rewritehtml", "callee": "replace", "source_file": "scripts/rewrite-cdn.mjs", "source_location": "L60"}, {"caller_nid": "rewrite_cdn_rewritehtml", "callee": "replace", "source_file": "scripts/rewrite-cdn.mjs", "source_location": "L67"}, {"caller_nid": "rewrite_cdn_rewritehtml", "callee": "replace", "source_file": "scripts/rewrite-cdn.mjs", "source_location": "L77"}, {"caller_nid": "rewrite_cdn_main", "callee": "now", "source_file": "scripts/rewrite-cdn.mjs", "source_location": "L86"}, {"caller_nid": "rewrite_cdn_main", "callee": "stat", "source_file": "scripts/rewrite-cdn.mjs", "source_location": "L89"}, {"caller_nid": "rewrite_cdn_main", "callee": "error", "source_file": "scripts/rewrite-cdn.mjs", "source_location": "L91"}, {"caller_nid": "rewrite_cdn_main", "callee": "exit", "source_file": "scripts/rewrite-cdn.mjs", "source_location": "L92"}, {"caller_nid": "rewrite_cdn_main", "callee": "isDirectory", "source_file": "scripts/rewrite-cdn.mjs", "source_location": "L94"}, {"caller_nid": "rewrite_cdn_main", "callee": "error", "source_file": "scripts/rewrite-cdn.mjs", "source_location": "L95"}, {"caller_nid": "rewrite_cdn_main", "callee": "exit", "source_file": "scripts/rewrite-cdn.mjs", "source_location": "L96"}, {"caller_nid": "rewrite_cdn_main", "callee": "walk", "source_file": "scripts/rewrite-cdn.mjs", "source_location": "L103"}, {"caller_nid": "rewrite_cdn_main", "callee": "readFile", "source_file": "scripts/rewrite-cdn.mjs", "source_location": "L105"}, {"caller_nid": "rewrite_cdn_main", "callee": "writeFile", "source_file": "scripts/rewrite-cdn.mjs", "source_location": "L108"}, {"caller_nid": "rewrite_cdn_main", "callee": "now", "source_file": "scripts/rewrite-cdn.mjs", "source_location": "L114"}, {"caller_nid": "rewrite_cdn_main", "callee": "log", "source_file": "scripts/rewrite-cdn.mjs", "source_location": "L115"}]}